sismic/__init__.py
sismic/exceptions.py
sismic/helpers.py
sismic/testing.py
sismic/utilities.py
sismic/bdd/__init__.py
sismic/bdd/__main__.py
sismic/bdd/environment.py
sismic/bdd/steps.py
sismic/bdd/wrappers.py
sismic/clock/__init__.py
sismic/clock/clock.py
sismic/code/__init__.py
sismic/code/context.py
sismic/code/dummy.py
sismic/code/evaluator.py
sismic/code/python.py
sismic/interpreter/__init__.py
sismic/interpreter/default.py
sismic/interpreter/listener.py
sismic/io/__init__.py
sismic/io/datadict.py
sismic/io/plantuml.py
sismic/io/yaml.py
sismic/model/__init__.py
sismic/model/elements.py
sismic/model/events.py
sismic/model/statechart.py
sismic/model/steps.py
sismic/runner/__init__.py
sismic/runner/runner.py
sismic-1.6.10.dist-info/licenses/AUTHORS.rst
sismic-1.6.10.dist-info/licenses/LICENSE
sismic-1.6.10.dist-info/METADATA
sismic-1.6.10.dist-info/WHEEL
sismic-1.6.10.dist-info/entry_points.txt
sismic-1.6.10.dist-info/top_level.txt
sismic-1.6.10.dist-info/zip-safe
sismic-1.6.10.dist-info/RECORD
